changelog_genie/__init__.py
changelog_genie/cli.py
changelog_genie-0.2.0.dist-info/entry_points.txt
changelog_genie-0.2.0.dist-info/LICENSE.txt
changelog_genie-0.2.0.dist-info/WHEEL
changelog_genie-0.2.0.dist-info/METADATA
changelog_genie-0.2.0.dist-info/RECORD
