Metadata-Version: 2.1
Name: changelog-genie
Version: 0.2.0
Summary: Generate changelogs for GitHub projects efficiently
Author: Andy Grove
Author-email: andygrove73@gmail.com
Requires-Python: >=3.7,<4.0
Classifier: Programming Language :: Python :: 3
Classifier: Programming Language :: Python :: 3.10
Classifier: Programming Language :: Python :: 3.7
Classifier: Programming Language :: Python :: 3.8
Classifier: Programming Language :: Python :: 3.9
